README.md
setup.py
bin/mmeowlink-any-pump-comms.py
bin/mmeowlink-bolus.py
bin/mmeowlink-rf-dump.py
bin/mmeowlink-send.py
bin/mmtune.py
mmeowlink/__init__.py
mmeowlink/detect_radio_comms.py
mmeowlink/exceptions.py
mmeowlink/fourbysix.py
mmeowlink/fuser.py
mmeowlink/hex_handling.py
mmeowlink/link_builder.py
mmeowlink/mmtune.py
mmeowlink.egg-info/PKG-INFO
mmeowlink.egg-info/SOURCES.txt
mmeowlink.egg-info/dependency_links.txt
mmeowlink.egg-info/not-zip-safe
mmeowlink.egg-info/requires.txt
mmeowlink.egg-info/top_level.txt
mmeowlink/cli/__init__.py
mmeowlink/cli/any_pump_comms_app.py
mmeowlink/cli/base_mmeowlink_app.py
mmeowlink/cli/bolus_app.py
mmeowlink/cli/mmtune_app.py
mmeowlink/cli/rf_dump_app.py
mmeowlink/cli/send_msg_app.py
mmeowlink/handlers/__init__.py
mmeowlink/handlers/stick.py
mmeowlink/packets/__init__.py
mmeowlink/packets/rf.py
mmeowlink/vendors/__init__.py
mmeowlink/vendors/mmcommander_link.py
mmeowlink/vendors/mmeowlink.py
mmeowlink/vendors/serial_interface.py
mmeowlink/vendors/serial_rf_spy.py
mmeowlink/vendors/subg_rfspy_link.py