Metadata-Version: 1.1
Name: mmeowlink
Version: 0.11.1
Summary: Driver layer for communicating with Medtronic pumps over a variety of radios
Home-page: https://github.com/oskarpearson/mmeowlink
Author: Oskar Pearson
Author-email: oskar+mmeowlink-pypi@deckle.co.uk
License: GPL
Platform: UNKNOWN
Classifier: Development Status :: 3 - Alpha
Classifier: Intended Audience :: Developers
Classifier: Intended Audience :: Science/Research
Classifier: License :: OSI Approved :: GNU General Public License v3 (GPLv3)
Classifier: Programming Language :: Python
Classifier: Topic :: Scientific/Engineering
Classifier: Topic :: Software Development :: Libraries
